{
  "menuCommands": [
    {
      "name": "MetaEdit: Run MetaEdit",
      "id": "metaedit:metaEditRun",
      "icon": "create-new"
    },
    {
      "name": "Tidy Footnotes: Tidy Footnotes",
      "id": "obsidian-tidy-footnotes:tidy-footnotes",
      "icon": "feather-compass"
    },
    {
      "name": "Templater: Open Insert Template modal",
      "id": "templater-obsidian:insert-templater",
      "icon": "spreadsheet"
    },
    {
      "name": "Title Serial Number Plugin: Set Serial Number For Title",
      "id": "obsidian-title-serial-number-plugin:set-title-serial-number-editor-command",
      "icon": "feather-zoom-in"
    },
    {
      "name": "Title Serial Number Plugin: Clear Serial Number For Title",
      "id": "obsidian-title-serial-number-plugin:clear-title-serial-number-editor-command",
      "icon": "feather-zoom-out"
    }
  ]
}